mzn_grader.py
mzn_grader-1.3.0.dist-info/entry_points.txt
mzn_grader-1.3.0.dist-info/LICENSE
mzn_grader-1.3.0.dist-info/WHEEL
mzn_grader-1.3.0.dist-info/METADATA
mzn_grader-1.3.0.dist-info/RECORD
